plasma/__init__.py
plasma/apa102.py
plasma/core.py
plasma/gpio.py
plasma/legacy.py
plasma/matrix.py
plasma/serial.py
plasma/usb.py
plasma/ws281x.py
plasmalights-2.0.2.dist-info/LICENSE.txt
plasmalights-2.0.2.dist-info/METADATA
plasmalights-2.0.2.dist-info/WHEEL
plasmalights-2.0.2.dist-info/top_level.txt
plasmalights-2.0.2.dist-info/RECORD
