Metadata-Version: 2.1
Name: plasmalights
Version: 2.0.2
Summary: Python library for driving Pimoroni Plasma and other LED devices
Home-page: https://www.pimoroni.com
Author: Philip Howard
Author-email: phil@pimoroni.com
License: MIT
Project-URL: GitHub, https://www.github.com/pimoroni/plasma
Keywords: Rasperry Pi LED
Platform: UNKNOWN
Classifier: Development Status :: 4 - Beta
Classifier: Operating System :: POSIX :: Linux
Classifier: License :: OSI Approved :: MIT License
Classifier: Intended Audience :: Developers
Classifier: Programming Language :: Python :: 3.7
Classifier: Topic :: Software Development
Classifier: Topic :: Software Development :: Libraries
Classifier: Topic :: System :: Hardware
Requires-Python: >=3.7
Requires-Dist: pyserial
Requires-Dist: pyyaml
